magelang/__init__.py
magelang/__main__.py
magelang/analysis.py
magelang/cli.py
magelang/eval.py
magelang/helpers.py
magelang/logging.py
magelang/main.py
magelang/manager.py
magelang/runtime.py
magelang/test_ast.py
magelang/test_runtime.py
magelang/test_util.py
magelang/util.py
magelang/ir/constants.py
magelang/ir/lexer.py
magelang/ir/parser.py
magelang/lang/mage/__init__.py
magelang/lang/mage/ast.py
magelang/lang/mage/constants.py
magelang/lang/mage/emitter.py
magelang/lang/mage/parser.py
magelang/lang/mage/scanner.py
magelang/lang/python/__init__.py
magelang/lang/python/cst.py
magelang/lang/python/emitter.py
magelang/lang/revolv/ast.py
magelang/lang/rust/__init__.py
magelang/lang/rust/cst.py
magelang/lang/rust/emitter.py
magelang/lang/treespec/__init__.py
magelang/lang/treespec/ast.py
magelang/lang/treespec/helpers.py
magelang/passes/__init__.py
magelang/passes/mage_add_prefix.py
magelang/passes/mage_check_neg_charset_intervals.py
magelang/passes/mage_check_overlapping_charset_intervals.py
magelang/passes/mage_check_token_no_parse.py
magelang/passes/mage_check_undefined.py
magelang/passes/mage_extract_literals.py
magelang/passes/mage_extract_prefixes.py
magelang/passes/mage_inline.py
magelang/passes/mage_insert_magic_rules.py
magelang/passes/mage_insert_skip.py
magelang/passes/mage_remove_hidden.py
magelang/passes/mage_simplify.py
magelang/passes/mage_to_python_emitter.py
magelang/passes/mage_to_revolv_syntax_tree.py
magelang/passes/mage_to_treespec.py
magelang/passes/python_to_text.py
magelang/passes/revolv_lift_assign_expr.py
magelang/passes/revolv_to_python.py
magelang/passes/revolv_to_rust.py
magelang/passes/rust_to_text.py
magelang/passes/treespec_cst_to_ast.py
magelang/passes/treespec_to_python.py
magelang-0.1.1.dist-info/LICENSE.txt
magelang-0.1.1.dist-info/METADATA
magelang-0.1.1.dist-info/WHEEL
magelang-0.1.1.dist-info/entry_points.txt
magelang-0.1.1.dist-info/top_level.txt
magelang-0.1.1.dist-info/RECORD
