Metadata-Version: 2.1
Name: magelang
Version: 0.1.1
Summary: A modern lexer/parser generator for a growing number of languages
Author-email: Sam Vervaeck <samvv@pm.me>
Maintainer-email: Sam Vervaeck <samvv@pm.me>
License: Copyright 2024 Sam Vervaeck
Project-URL: Homepage, https://github.com/samvv/mage
Project-URL: Bug Reports, https://github.com/samvv/mage/issues
Project-URL: Source, https://github.com/samvv/mage/
Keywords: text-analysis,scanner,lexer,parser,code-generator
Classifier: Development Status :: 3 - Alpha
Classifier: Intended Audience :: Developers
Classifier: Topic :: Software Development :: Code Generators
Classifier: License :: OSI Approved :: MIT License
Classifier: Programming Language :: Python :: 3
Classifier: Programming Language :: Python :: 3.8
Classifier: Programming Language :: Python :: 3.9
Classifier: Programming Language :: Python :: 3.10
Classifier: Programming Language :: Python :: 3.11
Classifier: Programming Language :: Python :: 3.12
Classifier: Programming Language :: Python :: 3 :: Only
Requires-Python: >=3.8
License-File: LICENSE.txt
Requires-Dist: marko
Requires-Dist: intervaltree
Provides-Extra: dev
Requires-Dist: check-manifest ; extra == 'dev'
Requires-Dist: GitPython ; extra == 'dev'
Provides-Extra: test
Requires-Dist: pytest ; extra == 'test'
Requires-Dist: coverage ; extra == 'test'
